{"1.0_server.md":"361459fc","1.0_client.md":"55c02bd6","1.0_clock.md":"99ac12b1","1.0_promise.md":"18c2127f","1.0_signal.md":"5bdfb935","1.1_client.md":"89b47ed7","1.1_clock.md":"ebe66e6d","1.1_promise.md":"3bbb20e6","1.1_red.md":"9fa3c07a","1.0_red.md":"0d1be9dc","1.1_server.md":"017fab7f","1.2_server.md":"94cf05bd","1.2_red.md":"785e7238","index.md":"15e4cd48","1.2_clock.md":"1718d4e5","1.2_promise.md":"84fcd9e7","1.2_signal.md":"b8ab710e","changelog.md":"80a544d2","guide_hacking-red_event-data-structure.md":"d1bc3bdc","1.2_client.md":"5baaa60a","guide_hacking-red_identifiers.md":"b3b5948e","guide_hacking-red_introduction.md":"fe4a8324","guide_introduction_installation-tooling.md":"9a132497","guide_introduction_what-is-red.md":"c4c12d51","guide_introduction_where-next-faq.md":"f8982812","guide_namespaces_listening-events.md":"5440ab6d","guide_namespaces_replicating-data.md":"375109b9","guide_namespaces_sending-invoking-events.md":"b2b3adcb","guide_namespaces_what-is-namespace.md":"cb0f3f57","1.1_signal.md":"782294d5"}
